symbolchain/AccountDescriptorRepository.py
symbolchain/ArrayHelpers.py
symbolchain/BaseValue.py
symbolchain/Bip32.py
symbolchain/BlockchainSettings.py
symbolchain/BufferReader.py
symbolchain/BufferWriter.py
symbolchain/ByteArray.py
symbolchain/Cipher.py
symbolchain/CodeWordsEncoder.py
symbolchain/CryptoTypes.py
symbolchain/DiceMnemonicGenerator.py
symbolchain/Network.py
symbolchain/NetworkTimestamp.py
symbolchain/NodeDescriptorRepository.py
symbolchain/Ordered.py
symbolchain/PrivateKeyStorage.py
symbolchain/QrSignatureStorage.py
symbolchain/QrStorage.py
symbolchain/RuleBasedTransactionFactory.py
symbolchain/SharedKey.py
symbolchain/TransactionDescriptorProcessor.py
symbolchain/Transforms.py
symbolchain/__init__.py
symbolchain/external/__init__.py
symbolchain/external/ed25519.py
symbolchain/facade/BatchOperations.py
symbolchain/facade/NemFacade.py
symbolchain/facade/SymbolFacade.py
symbolchain/facade/__init__.py
symbolchain/impl/CipherHelpers.py
symbolchain/impl/__init__.py
symbolchain/nc/__init__.py
symbolchain/nem/KeyPair.py
symbolchain/nem/MessageEncoder.py
symbolchain/nem/Network.py
symbolchain/nem/SharedKey.py
symbolchain/nem/TransactionFactory.py
symbolchain/nem/__init__.py
symbolchain/ripemd160.py
symbolchain/sc/__init__.py
symbolchain/symbol/IdGenerator.py
symbolchain/symbol/KeyPair.py
symbolchain/symbol/Merkle.py
symbolchain/symbol/MessageEncoder.py
symbolchain/symbol/Metadata.py
symbolchain/symbol/Network.py
symbolchain/symbol/SharedKey.py
symbolchain/symbol/TransactionFactory.py
symbolchain/symbol/VotingKeysGenerator.py
symbolchain/symbol/__init__.py
symbol_sdk_python-3.3.0.dist-info/METADATA
symbol_sdk_python-3.3.0.dist-info/WHEEL
symbol_sdk_python-3.3.0.dist-info/RECORD
