Metadata-Version: 2.1
Name: symbol-sdk-python
Version: 3.3.0
Summary: Symbol SDK
Home-page: https://github.com/symbol/symbol/tree/main/sdk/python
License: MIT
Keywords: symbol,sdk,Symbol SDK
Author: Symbol Contributors
Author-email: contributors@symbol.dev
Maintainer: Symbol Contributors
Maintainer-email: contributors@symbol.dev
Requires-Python: >=3.9.2,<4.0.0
Classifier: License :: OSI Approved :: MIT License
Classifier: Programming Language :: Python :: 3
Classifier: Programming Language :: Python :: 3.10
Classifier: Programming Language :: Python :: 3.11
Classifier: Programming Language :: Python :: 3.12
Classifier: Programming Language :: Python :: 3.13
Classifier: Programming Language :: Python :: 3.9
Requires-Dist: cryptography (>=46.0.1,<46.1.0)
Requires-Dist: mnemonic (>=0.20,<1.0)
Requires-Dist: pillow (>=11.3.0,<11.4.0)
Requires-Dist: pynacl (>=1.6.0,<1.7.0)
Requires-Dist: pyyaml (>=6.0.1,<6.1.0)
Requires-Dist: pyzbar (>=0.1.9,<0.2.0)
Requires-Dist: qrcode (>=8.0,<9.0)
Requires-Dist: ripemd-hash (>=1.0.1,<1.1.0)
Requires-Dist: safe-pysha3 (>=1.0.4,<1.1.0)
Project-URL: Repository, https://github.com/symbol/symbol/tree/main/sdk/python
